{"timestamp": "2025-04-30T23:53:56.992544", "level": "INFO", "message": "Database connection established", "module": "db_handler", "function": "_init_db", "line": 26, "process": 2560, "thread": "MainThread"}
{"timestamp": "2025-04-30T23:53:59.223622", "level": "INFO", "message": "Database tables verified/created", "module": "__init__", "function": "create_app", "line": 43, "process": 2560, "thread": "MainThread"}
{"timestamp": "2025-04-30T23:53:59.224042", "level": "INFO", "message": "Application initialized successfully", "module": "__init__", "function": "create_app", "line": 48, "process": 2560, "thread": "MainThread"}
{"timestamp": "2025-04-30T23:54:16.883611", "level": "WARNING", "message": "Not found: 404 Not Found: The requested URL was not found on the server. If you entered the URL manually please check your spelling and try again.", "module": "__init__", "function": "not_found", "line": 68, "process": 2560, "thread": "Thread-2 (process_request_thread)"}
{"timestamp": "2025-05-01T00:06:00.316373", "level": "WARNING", "message": "Not found: 404 Not Found: The requested URL was not found on the server. If you entered the URL manually please check your spelling and try again.", "module": "__init__", "function": "not_found", "line": 68, "process": 2560, "thread": "Thread-3 (process_request_thread)"}
{"timestamp": "2025-05-01T00:15:03.480375", "level": "WARNING", "message": "Not found: 404 Not Found: The requested URL was not found on the server. If you entered the URL manually please check your spelling and try again.", "module": "__init__", "function": "not_found", "line": 68, "process": 2560, "thread": "Thread-5 (process_request_thread)"}
{"timestamp": "2025-05-01T00:24:08.736186", "level": "INFO", "message": "Database connection established", "module": "db_handler", "function": "_init_db", "line": 26, "process": 21176, "thread": "MainThread"}
{"timestamp": "2025-05-01T00:24:11.403955", "level": "INFO", "message": "Database tables verified/created", "module": "__init__", "function": "create_app", "line": 43, "process": 21176, "thread": "MainThread"}
{"timestamp": "2025-05-01T00:24:11.404315", "level": "INFO", "message": "Application initialized successfully", "module": "__init__", "function": "create_app", "line": 48, "process": 21176, "thread": "MainThread"}
{"timestamp": "2025-05-01T00:24:30.611825", "level": "WARNING", "message": "Not found: 404 Not Found: The requested URL was not found on the server. If you entered the URL manually please check your spelling and try again.", "module": "__init__", "function": "not_found", "line": 68, "process": 21176, "thread": "Thread-2 (process_request_thread)"}
{"timestamp": "2025-05-01T00:39:14.780213", "level": "INFO", "message": "Database connection established", "module": "db_handler", "function": "_init_db", "line": 26, "process": 10164, "thread": "MainThread"}
{"timestamp": "2025-05-01T00:39:16.856939", "level": "INFO", "message": "Database tables verified/created", "module": "__init__", "function": "create_app", "line": 43, "process": 10164, "thread": "MainThread"}
{"timestamp": "2025-05-01T00:39:16.857251", "level": "INFO", "message": "Application initialized successfully", "module": "__init__", "function": "create_app", "line": 48, "process": 10164, "thread": "MainThread"}
{"timestamp": "2025-05-01T00:39:29.272627", "level": "WARNING", "message": "Not found: 404 Not Found: The requested URL was not found on the server. If you entered the URL manually please check your spelling and try again.", "module": "__init__", "function": "not_found", "line": 68, "process": 10164, "thread": "Thread-2 (process_request_thread)"}
{"timestamp": "2025-05-01T01:11:12.607587", "level": "INFO", "message": "Database connection established", "module": "db_handler", "function": "_init_db", "line": 26, "process": 16292, "thread": "MainThread"}
{"timestamp": "2025-05-01T01:11:15.012332", "level": "INFO", "message": "Database tables verified/created", "module": "__init__", "function": "create_app", "line": 43, "process": 16292, "thread": "MainThread"}
{"timestamp": "2025-05-01T01:11:15.012666", "level": "INFO", "message": "Application initialized successfully", "module": "__init__", "function": "create_app", "line": 48, "process": 16292, "thread": "MainThread"}
{"timestamp": "2025-05-01T01:11:31.776412", "level": "WARNING", "message": "Not found: 404 Not Found: The requested URL was not found on the server. If you entered the URL manually please check your spelling and try again.", "module": "__init__", "function": "not_found", "line": 68, "process": 16292, "thread": "Thread-2 (process_request_thread)"}
